darkmark/__about__.py
darkmark/__init__.py
darkmark/__main__.py
darkmark/console.py
darkmark/darkmark.py
darkmark/replacer.py
darkmark/cli/__init__.py
darkmark/cli/common.py
darkmark-0.2.0.dist-info/METADATA
darkmark-0.2.0.dist-info/WHEEL
darkmark-0.2.0.dist-info/entry_points.txt
darkmark-0.2.0.dist-info/licenses/LICENSE.txt
darkmark-0.2.0.dist-info/RECORD
