Metadata-Version: 2.1
Name: darkmark
Version: 0.2.0
Summary: Execute codeblocks inside of markdown
Project-URL: Documentation, https://github.com/unknown/darkmark#readme
Project-URL: Issues, https://github.com/unknown/darkmark/issues
Project-URL: Source, https://github.com/unknown/darkmark
Author-email: "Waylon S. Walker" <waylon@waylonwalker.com>
License-Expression: MIT
License-File: LICENSE.txt
Classifier: Development Status :: 4 - Beta
Classifier: Programming Language :: Python
Classifier: Programming Language :: Python :: 3.7
Classifier: Programming Language :: Python :: 3.8
Classifier: Programming Language :: Python :: 3.9
Classifier: Programming Language :: Python :: 3.10
Classifier: Programming Language :: Python :: 3.11
Classifier: Programming Language :: Python :: Implementation :: CPython
Classifier: Programming Language :: Python :: Implementation :: PyPy
Requires-Python: >=3.7
Requires-Dist: checksumdir
Requires-Dist: ipython
Requires-Dist: pyflyby
Requires-Dist: rich
Requires-Dist: tree-sitter-languages
Requires-Dist: typer
Provides-Extra: tui
Requires-Dist: trogon; extra == 'tui'
